fsvisual/__init__.py
fsvisual/brillouin_zone.py
fsvisual/cli.py
fsvisual/fermisurface.py
fsvisual/input.py
fsvisual/mesh.py
fsvisual/visualisation.py
fsvisual-0.0.1.dist-info/licenses/LICENSE
fsvisual-0.0.1.dist-info/METADATA
fsvisual-0.0.1.dist-info/WHEEL
fsvisual-0.0.1.dist-info/entry_points.txt
fsvisual-0.0.1.dist-info/top_level.txt
fsvisual-0.0.1.dist-info/RECORD
